fluffy_disco-1.0.0-py3.9-nspkg.pth
pds/fluffydisco/VERSION.txt
pds/fluffydisco/__init__.py
pds/fluffydisco/main.py
fluffy_disco-1.0.0.dist-info/LICENSE.md
fluffy_disco-1.0.0.dist-info/METADATA
fluffy_disco-1.0.0.dist-info/NOTICE.txt
fluffy_disco-1.0.0.dist-info/WHEEL
fluffy_disco-1.0.0.dist-info/entry_points.txt
fluffy_disco-1.0.0.dist-info/namespace_packages.txt
fluffy_disco-1.0.0.dist-info/top_level.txt
fluffy_disco-1.0.0.dist-info/zip-safe
fluffy_disco-1.0.0.dist-info/RECORD
