Metadata-Version: 2.1
Name: fluffy-disco
Version: 1.0.0
Summary: A demo only
Home-page: https://github.com/nutjob4life/fluffy-disco/
Download-URL: https://github.com/nutjob4life/fluffy-disco/releases/
Author: PDS
Author-email: pds_operator@jpl.nasa.gov
License: apache-2.0
Keywords: demo,throwaway
Classifier: Programming Language :: Python :: 3
Classifier: Programming Language :: Python :: 3.9
Classifier: License :: OSI Approved :: Apache Software License
Classifier: Operating System :: OS Independent
Requires-Python: >=3.9
License-File: LICENSE.md
License-File: NOTICE.txt
Provides-Extra: dev
Requires-Dist: black ; extra == 'dev'
Requires-Dist: flake8 ; extra == 'dev'
Requires-Dist: flake8-bugbear ; extra == 'dev'
Requires-Dist: flake8-docstrings ; extra == 'dev'
Requires-Dist: pep8-naming ; extra == 'dev'
Requires-Dist: mypy ; extra == 'dev'
Requires-Dist: pydocstyle ; extra == 'dev'
Requires-Dist: coverage ; extra == 'dev'
Requires-Dist: pytest ; extra == 'dev'
Requires-Dist: pytest-cov ; extra == 'dev'
Requires-Dist: pytest-watch ; extra == 'dev'
Requires-Dist: pytest-xdist ; extra == 'dev'
Requires-Dist: pre-commit ; extra == 'dev'
Requires-Dist: sphinx ; extra == 'dev'
Requires-Dist: sphinx-rtd-theme ; extra == 'dev'
Requires-Dist: tox ; extra == 'dev'
Requires-Dist: types-setuptools ; extra == 'dev'
